balance_nubank/__init__.py
balance_nubank/auth_mode.py
balance_nubank/cli.py
balance_nubank/exception.py
balance_nubank/nubank.py
balance_nubank/queries/account_balance.gql
balance_nubank/queries/account_feed.gql
balance_nubank/queries/account_feed_paginated.gql
balance_nubank/queries/account_id.gql
balance_nubank/queries/account_investments.gql
balance_nubank/queries/account_investments_yield.gql
balance_nubank/queries/account_savings.gql
balance_nubank/queries/create_boleto.gql
balance_nubank/queries/create_money_request.gql
balance_nubank/queries/create_pix_money_request.gql
balance_nubank/queries/get_pix_keys.gql
balance_nubank/queries/pix_receipt_screen.gql
balance_nubank/utils/__init__.py
balance_nubank/utils/certificate_generator.py
balance_nubank/utils/discovery.py
balance_nubank/utils/graphql.py
balance_nubank/utils/http.py
balance_nubank/utils/mock_http.py
balance_nubank/utils/parsing.py
balance_nubank/utils/mocked_responses/__init__.py
balance_nubank/utils/mocked_responses/account.json
balance_nubank/utils/mocked_responses/account_balance.json
balance_nubank/utils/mocked_responses/account_feed.json
balance_nubank/utils/mocked_responses/account_feed_paginated.json
balance_nubank/utils/mocked_responses/account_investments.json
balance_nubank/utils/mocked_responses/account_investments_yield.json
balance_nubank/utils/mocked_responses/account_savings.json
balance_nubank/utils/mocked_responses/bills.json
balance_nubank/utils/mocked_responses/bills_summary.json
balance_nubank/utils/mocked_responses/boleto_create.json
balance_nubank/utils/mocked_responses/card_statement_detail.json
balance_nubank/utils/mocked_responses/customer.json
balance_nubank/utils/mocked_responses/discovery_api.json
balance_nubank/utils/mocked_responses/discovery_app.json
balance_nubank/utils/mocked_responses/discovery_login.json
balance_nubank/utils/mocked_responses/discovery_login_alternative.json
balance_nubank/utils/mocked_responses/money.json
balance_nubank-1.0.7.dist-info/METADATA
balance_nubank-1.0.7.dist-info/WHEEL
balance_nubank-1.0.7.dist-info/top_level.txt
balance_nubank-1.0.7.dist-info/RECORD
