Metadata-Version: 2.1
Name: balance-nubank
Version: 1.0.7
Summary: Objetivos:
Home-page: https://pypi.org/project/balance-service
Author: Calenzo
Author-email: calenzodevs@gmail.com
License: MIT License
Classifier: Programming Language :: Python :: 3.7
Classifier: Programming Language :: Python :: 3.8
Classifier: Natural Language :: English
Classifier: License :: OSI Approved :: MIT License
Classifier: Operating System :: OS Independent
Requires-Dist: requests (==2.28.1)
Requires-Dist: qrcode (==7.3.1)
Requires-Dist: pyOpenSSL (==22.1.0)
Requires-Dist: colorama (==0.4.6)
Requires-Dist: requests-pkcs12 (==1.14)
Requires-Dist: Deprecated (==1.2.13)
